{
	"id": "battle_001",
	"name": "Roadside Ambush",
	"title": "路旁伏击",
	"background_path": "res://assets/battle/background/battle_ground.png",
	"ui_note": "先稳住阵型，再找机会切入。",
	"board": {
		"columns": 8,
		"rows": 8
	},
	"terrain": [
		{
			"cell": [3, 2],
			"type": "stone"
		},
		{
			"cell": [3, 3],
			"type": "water"
		},
		{
			"cell": [4, 4],
			"type": "stone"
		}
	],
	"player": {
		"formation_slot": 1
	},
	"enemies": {
		"units": [
			{
				"instance_id": "bandit_a",
				"template_id": "bandit_raider"
			},
			{
				"instance_id": "bandit_b",
				"template_id": "bandit_raider"
			}
		],
		"formation_pool": ["bandit_line", "bandit_hook"]
	},
	"ai_difficulty": "normal",
	"victory_conditions": [
		{
			"type": "all_enemies_defeated"
		}
	],
	"defeat_conditions": [
		{
			"type": "all_allies_defeated"
		}
	]
}
